ONAL/__init__.py
ONAL/classes/__init__.py
ONAL/classes/directed_graph.py
ONAL/classes/graph.py
ONAL/functions/__init__.py
ONAL/functions/community/__init__.py
ONAL/functions/community/modularity.py
ONAL/functions/community/modularity_max_detection.py
ONAL/functions/components/__init__.py
ONAL/functions/components/biconnected.py
ONAL/functions/components/connected.py
ONAL/functions/graph_embedding/__init__.py
ONAL/functions/graph_embedding/node2vec.py
ONAL/functions/graph_embedding/node2vec/__init__.py
ONAL/functions/graph_embedding/node2vec/edges.py
ONAL/functions/graph_embedding/node2vec/node2vec.py
ONAL/functions/graph_embedding/node2vec/parallel.py
ONAL/functions/not_sorted/__init__.py
ONAL/functions/not_sorted/pagerank.py
ONAL/functions/structural_holes/AP_Greedy.py
ONAL/functions/structural_holes/HAM.py
ONAL/functions/structural_holes/HIS.py
ONAL/functions/structural_holes/MaxD.py
ONAL/functions/structural_holes/__init__.py
ONAL/tests/__init__.py
ONAL/tests/test_1.py
ONAL/tests/test_2.py
ONAL/tests/utils.py
ONAL/utils/__init__.py
ONAL/utils/convert_to_matrix.py
ONAL/utils/decorators.py
ONAL/utils/mapped_queue.py
ONAL-0.0.1.dist-info/LICENSE
ONAL-0.0.1.dist-info/METADATA
ONAL-0.0.1.dist-info/WHEEL
ONAL-0.0.1.dist-info/top_level.txt
ONAL-0.0.1.dist-info/RECORD
